[{"paths": ["group1-shard1of1"], "weights": [{"dtype": "float32", "shape": [], "name": "Const"}, {"dtype": "float32", "shape": [3, 3, 1, 8], "name": "l1/kernel"}, {"dtype": "float32", "shape": [8], "name": "l1/bias"}, {"dtype": "float32", "shape": [3, 3, 8, 16], "name": "l2/kernel"}, {"dtype": "float32", "shape": [16], "name": "l2/bias"}, {"dtype": "float32", "shape": [3, 3, 16, 32], "name": "l3/kernel"}, {"dtype": "float32", "shape": [32], "name": "l3/bias"}, {"dtype": "int32", "shape": [1], "name": "flatten/strided_slice/stack"}, {"dtype": "int32", "shape": [1], "name": "flatten/strided_slice/stack_1"}, {"dtype": "int32", "shape": [], "name": "flatten/Reshape/shape/1"}, {"dtype": "float32", "shape": [128, 100], "name": "l4/kernel"}, {"dtype": "float32", "shape": [100], "name": "l4/bias"}, {"dtype": "float32", "shape": [100, 10], "name": "l5/kernel"}, {"dtype": "float32", "shape": [10], "name": "l5/bias"}]}]